pyqcolor/__init__.py
pyqcolor/test.py
pyqcolor-1.1.dist-info/METADATA
pyqcolor-1.1.dist-info/WHEEL
pyqcolor-1.1.dist-info/top_level.txt
pyqcolor-1.1.dist-info/RECORD
