Metadata-Version: 2.1
Name: pyqcolor
Version: 1.1
Summary: Bring Colorful Code
Author-email: smithsha@gmail.com
License: Eclipse Public License 2.0
